src/ElGamal.py
src/__init__.py
elgamal_anass_daniel-0.0.4.dist-info/METADATA
elgamal_anass_daniel-0.0.4.dist-info/WHEEL
elgamal_anass_daniel-0.0.4.dist-info/top_level.txt
elgamal_anass_daniel-0.0.4.dist-info/RECORD
