Metadata-Version: 2.1
Name: elgamal_anass_daniel
Version: 0.0.4
Summary: ElGamal encryption
Home-page: UNKNOWN
Author: Anass Anhari & Daniel Alamillo
Author-email: <anassanhari@estudiantat-upc.edu>
License: UNKNOWN
Keywords: python,elgamal,encryption,chyper
Platform: UNKNOWN
Classifier: Development Status :: 1 - Planning
Classifier: Intended Audience :: Developers
Classifier: Programming Language :: Python :: 3
Classifier: Operating System :: Unix
Classifier: Operating System :: MacOS :: MacOS X
Classifier: Operating System :: Microsoft :: Windows
